tryton_filestore_s3.py
tryton_filestore_s3-0.2.1.dist-info/LICENSE
tryton_filestore_s3-0.2.1.dist-info/METADATA
tryton_filestore_s3-0.2.1.dist-info/WHEEL
tryton_filestore_s3-0.2.1.dist-info/top_level.txt
tryton_filestore_s3-0.2.1.dist-info/RECORD
