Metadata-Version: 2.1
Name: tryton-filestore-s3
Version: 0.2.1
Summary: Store Tryton files on S3 AWS Storage.
Home-page: https://github.com/gcoop-libre/tryton-filestore-s3
Author: gcoop
Author-email: info@gcoop.coop
License: GPL-3
Keywords: tryton s3 aws storage attachments
Platform: Posix; MacOS X; Windows
Classifier: Framework :: Tryton
Classifier: Intended Audience :: Developers
Classifier: License :: OSI Approved :: GNU General Public License (GPL)
Classifier: Operating System :: OS Independent
Classifier: Programming Language :: Python :: 3.6
Classifier: Programming Language :: Python :: 3.7
Classifier: Programming Language :: Python :: 3.8
Classifier: Programming Language :: Python :: 3.9
Classifier: Topic :: Internet
Requires-Dist: boto3
Requires-Dist: trytond (>4.2)
